{
  "entities": {
    "User": {
      "title": "User Profile",
      "description": "Public and private information for a user",
      "type": "object",
      "properties": {
        "uid": { "type": "string" },
        "displayName": { "type": "string" },
        "photoURL": { "type": "string" },
        "bio": { "type": "string" },
        "location": { "type": "string" },
        "studiedAt": { "type": "string" },
        "friendsCount": { "type": "number" },
        "createdAt": { "type": "string", "format": "date-time" }
      },
      "required": ["uid", "displayName"]
    },
    "Post": {
      "title": "Social Post",
      "description": "A post in the newsfeed",
      "type": "object",
      "properties": {
        "authorId": { "type": "string" },
        "authorName": { "type": "string" },
        "authorAvatar": { "type": "string" },
        "content": { "type": "string" },
        "imageUrl": { "type": "string" },
        "likesCount": { "type": "number" },
        "commentsCount": { "type": "number" },
        "createdAt": { "type": "string", "format": "date-time" }
      },
      "required": ["authorId", "content", "createdAt"]
    },
    "Message": {
      "title": "Chat Message",
      "description": "A message in a conversation",
      "type": "object",
      "properties": {
        "chatId": { "type": "string" },
        "senderId": { "type": "string" },
        "text": { "type": "string" },
        "createdAt": { "type": "string", "format": "date-time" }
      },
      "required": ["chatId", "senderId", "text", "createdAt"]
    }
  },
  "firestore": {
    "/users/{userId}": {
      "schema": "User",
      "description": "User profile documents"
    },
    "/posts/{postId}": {
      "schema": "Post",
      "description": "Newsfeed posts"
    },
    "/chats/{chatId}/messages/{messageId}": {
      "schema": "Message",
      "description": "Messages within a specific chat"
    }
  }
}
